README.md
setup.cfg
setup.py
cloudmersive_voicerecognition_api_client/__init__.py
cloudmersive_voicerecognition_api_client/api_client.py
cloudmersive_voicerecognition_api_client/configuration.py
cloudmersive_voicerecognition_api_client/rest.py
cloudmersive_voicerecognition_api_client.egg-info/PKG-INFO
cloudmersive_voicerecognition_api_client.egg-info/SOURCES.txt
cloudmersive_voicerecognition_api_client.egg-info/dependency_links.txt
cloudmersive_voicerecognition_api_client.egg-info/requires.txt
cloudmersive_voicerecognition_api_client.egg-info/top_level.txt
cloudmersive_voicerecognition_api_client/api/__init__.py
cloudmersive_voicerecognition_api_client/api/recognize_api.py
cloudmersive_voicerecognition_api_client/api/speak_api.py
cloudmersive_voicerecognition_api_client/models/__init__.py
cloudmersive_voicerecognition_api_client/models/speech_recognition_result.py
cloudmersive_voicerecognition_api_client/models/text_to_speech_request.py
test/__init__.py
test/test_recognize_api.py
test/test_speak_api.py
test/test_speech_recognition_result.py
test/test_text_to_speech_request.py