Metadata-Version: 2.1
Name: cloudmersive-voicerecognition-api-client
Version: 4.0.1
Summary: speechapi
Home-page: https://cloudmersive.com/voice-recognition-and-speech-api
Author-email: 
License: UNKNOWN
Keywords: Swagger,speechapi
Platform: UNKNOWN
